log_service_proto/__init__.py
log_service_proto/models/__init__.py
log_service_proto/models/log_message_pb2.py
log_service_proto/models/log_message_pb2_grpc.py
log_service_proto/services/__init__.py
log_service_proto/services/log_service_pb2.py
log_service_proto/services/log_service_pb2_grpc.py
jocampo_log_service_proto-0.0.3.dist-info/LICENSE
jocampo_log_service_proto-0.0.3.dist-info/METADATA
jocampo_log_service_proto-0.0.3.dist-info/WHEEL
jocampo_log_service_proto-0.0.3.dist-info/top_level.txt
jocampo_log_service_proto-0.0.3.dist-info/RECORD
