Metadata-Version: 2.1
Name: jocampo-log-service-proto
Version: 0.0.3
Summary: Python definitions for a basic Log Service
Home-page: https://github.com/jocampo/log_service_proto
Author: Jorge Ocampo
Author-email: jorge.luis.ocampo.mascaro@gmail.com
License: UNKNOWN
Project-URL: Bug Tracker, https://github.com/jocampo/log_service_proto/issues
Platform: UNKNOWN
Classifier: Programming Language :: Python :: 3
Classifier: License :: OSI Approved :: MIT License
Classifier: Operating System :: OS Independent
License-File: LICENSE
